UnitTest/__init__.py
tradeSim/Execution.py
tradeSim/Order.py
tradeSim/PortSummarize.py
tradeSim/Portfolio.py
tradeSim/Stock.py
tradeSim/Symbol_SET50.csv
tradeSim/TradeSim.py
tradeSim/TransactionLog.py
tradeSim/__init__.py
tradesim_coptee-0.1.7.dist-info/licenses/LICENSE
tradesim_coptee-0.1.7.dist-info/METADATA
tradesim_coptee-0.1.7.dist-info/WHEEL
tradesim_coptee-0.1.7.dist-info/top_level.txt
tradesim_coptee-0.1.7.dist-info/RECORD
